odoo9_addon_account_fiscal_position_vat_check-9.0.1.0.0-py2.7-nspkg.pth
odoo_addons/account_fiscal_position_vat_check/__openerp__.py
odoo_addons/account_fiscal_position_vat_check/__init__.py
odoo_addons/account_fiscal_position_vat_check/README.rst
odoo_addons/account_fiscal_position_vat_check/models/account_invoice.py
odoo_addons/account_fiscal_position_vat_check/models/partner.py
odoo_addons/account_fiscal_position_vat_check/models/__init__.py
odoo_addons/account_fiscal_position_vat_check/i18n/pt.po
odoo_addons/account_fiscal_position_vat_check/i18n/es.po
odoo_addons/account_fiscal_position_vat_check/i18n/hr.po
odoo_addons/account_fiscal_position_vat_check/i18n/bg.po
odoo_addons/account_fiscal_position_vat_check/i18n/pt_PT.po
odoo_addons/account_fiscal_position_vat_check/i18n/de.po
odoo_addons/account_fiscal_position_vat_check/views/account_fiscal_position_view.xml
odoo9_addon_account_fiscal_position_vat_check-9.0.1.0.0.dist-info/top_level.txt
odoo9_addon_account_fiscal_position_vat_check-9.0.1.0.0.dist-info/WHEEL
odoo9_addon_account_fiscal_position_vat_check-9.0.1.0.0.dist-info/RECORD
odoo9_addon_account_fiscal_position_vat_check-9.0.1.0.0.dist-info/metadata.json
odoo9_addon_account_fiscal_position_vat_check-9.0.1.0.0.dist-info/DESCRIPTION.rst
odoo9_addon_account_fiscal_position_vat_check-9.0.1.0.0.dist-info/METADATA
odoo9_addon_account_fiscal_position_vat_check-9.0.1.0.0.dist-info/namespace_packages.txt
